sj201_interface/__init__.py
sj201_interface/cli.py
sj201_interface/fan.py
sj201_interface/log.py
sj201_interface/revisions.py
sj201_interface/switches.py
sj201_interface/version.py
sj201_interface/led/__init__.py
sj201_interface/led/animations.py
sj201_interface/util/__init__.py
sj201_interface/util/patches.py
sj201_interface/util/pwmcontroller.py
sj201_interface/util/tas5806.py
sj201_interface-0.1.0.dist-info/LICENSE.md
sj201_interface-0.1.0.dist-info/METADATA
sj201_interface-0.1.0.dist-info/WHEEL
sj201_interface-0.1.0.dist-info/entry_points.txt
sj201_interface-0.1.0.dist-info/top_level.txt
sj201_interface-0.1.0.dist-info/RECORD
