Metadata-Version: 2.1
Name: sj201-interface
Version: 0.1.0
Summary: SJ201 Interface
Home-page: https://github.com/NeonGeckoCom/sj201-interface
Author: Neongecko
Author-email: developers@neon.ai
License: BSD-3
License-File: LICENSE.md
Requires-Dist: RPi.GPIO~=0.7
Requires-Dist: smbus2~=0.4
Requires-Dist: click~=8.0
Requires-Dist: click-default-group~=1.2
Requires-Dist: rpi-ws281x~=4.3
Requires-Dist: adafruit-circuitpython-neopixel~=6.3
Requires-Dist: adafruit-blinka~=8.6
Requires-Dist: spidev~=3.5
